{
  "dataset_revision": "d80d48c1eb48d3562165c59d59d0034df9fff0bf",
  "evaluation_time": 14.58607268333435,
  "kg_co2_emissions": null,
  "mteb_version": "1.14.20",
  "scores": {
    "test": [
      {
        "accuracy": 0.4147058823529412,
        "f1": 0.4048591466071335,
        "f1_weighted": 0.4189291028431736,
        "hf_subset": "en",
        "languages": [
          "eng-Latn"
        ],
        "main_score": 0.4147058823529412,
        "scores_per_experiment": [
          {
            "accuracy": 0.37254901960784315,
            "f1": 0.3709648786357626,
            "f1_weighted": 0.3734274613075656
          },
          {
            "accuracy": 0.4238486092111263,
            "f1": 0.4247948386921335,
            "f1_weighted": 0.43518613514297866
          },
          {
            "accuracy": 0.415640674874601,
            "f1": 0.4013368036960559,
            "f1_weighted": 0.4215586042720343
          },
          {
            "accuracy": 0.4069767441860465,
            "f1": 0.3915309686932514,
            "f1_weighted": 0.4116912283306865
          },
          {
            "accuracy": 0.4434564523483812,
            "f1": 0.4303667656126582,
            "f1_weighted": 0.4515091737513478
          },
          {
            "accuracy": 0.4297765617875057,
            "f1": 0.4256658669162477,
            "f1_weighted": 0.4308833067008713
          },
          {
            "accuracy": 0.39238486092111263,
            "f1": 0.36956598097697757,
            "f1_weighted": 0.3925588189304878
          },
          {
            "accuracy": 0.36753305973552214,
            "f1": 0.3611968834128268,
            "f1_weighted": 0.37254873673509764
          },
          {
            "accuracy": 0.421796625626995,
            "f1": 0.4151303880719372,
            "f1_weighted": 0.4292853057560521
          },
          {
            "accuracy": 0.47309621523027817,
            "f1": 0.4580380913634849,
            "f1_weighted": 0.47064225750461386
          }
        ]
      }
    ]
  },
  "task_name": "MTOPDomainClassification"
}