{
  "dataset_revision": "4672e20407010da34463acc759c162ca9734bca6",
  "evaluation_time": 672.3684804439545,
  "kg_co2_emissions": null,
  "mteb_version": "1.14.19",
  "scores": {
    "test": [
      {
        "accuracy": 0.6139542703429723,
        "f1": 0.5832967953053514,
        "f1_weighted": 0.6163368981382519,
        "hf_subset": "en",
        "languages": [
          "eng-Latn"
        ],
        "main_score": 0.6139542703429723,
        "scores_per_experiment": [
          {
            "accuracy": 0.6153328850033625,
            "f1": 0.6015114766819267,
            "f1_weighted": 0.615614273961874
          },
          {
            "accuracy": 0.6281102891728312,
            "f1": 0.5961431906873795,
            "f1_weighted": 0.6308845975822455
          },
          {
            "accuracy": 0.6099529253530599,
            "f1": 0.568294043617247,
            "f1_weighted": 0.6071745161836676
          },
          {
            "accuracy": 0.6408876933422999,
            "f1": 0.5945238349088604,
            "f1_weighted": 0.6431124716163543
          },
          {
            "accuracy": 0.6156691324815063,
            "f1": 0.5805446592181164,
            "f1_weighted": 0.6141332152482704
          },
          {
            "accuracy": 0.5931405514458642,
            "f1": 0.5721294385718225,
            "f1_weighted": 0.59954542551636
          },
          {
            "accuracy": 0.6109616677874916,
            "f1": 0.5888488548560669,
            "f1_weighted": 0.6148839643666086
          },
          {
            "accuracy": 0.6028917283120376,
            "f1": 0.5672227602528157,
            "f1_weighted": 0.6091515276912862
          },
          {
            "accuracy": 0.6035642232683255,
            "f1": 0.5765634673670944,
            "f1_weighted": 0.6058962059045527
          },
          {
            "accuracy": 0.6190316072629455,
            "f1": 0.5871862268921839,
            "f1_weighted": 0.6229727833112997
          }
        ]
      }
    ],
    "validation": [
      {
        "accuracy": 0.6202164289227742,
        "f1": 0.5922574066657024,
        "f1_weighted": 0.6216172959497814,
        "hf_subset": "en",
        "languages": [
          "eng-Latn"
        ],
        "main_score": 0.6202164289227742,
        "scores_per_experiment": [
          {
            "accuracy": 0.602065912444663,
            "f1": 0.5870699363425854,
            "f1_weighted": 0.6021492768730504
          },
          {
            "accuracy": 0.6438760452533202,
            "f1": 0.611320502742744,
            "f1_weighted": 0.6424170984573956
          },
          {
            "accuracy": 0.6330545991146089,
            "f1": 0.5978908015581258,
            "f1_weighted": 0.6301147616823449
          },
          {
            "accuracy": 0.6369896704377767,
            "f1": 0.5924631570954303,
            "f1_weighted": 0.6382343162051904
          },
          {
            "accuracy": 0.6232169208066897,
            "f1": 0.5967623063151102,
            "f1_weighted": 0.6242731394911414
          },
          {
            "accuracy": 0.5932120019675357,
            "f1": 0.5818907363684577,
            "f1_weighted": 0.5978100591134415
          },
          {
            "accuracy": 0.5981308411214953,
            "f1": 0.577497168052736,
            "f1_weighted": 0.60137802993592
          },
          {
            "accuracy": 0.6192818494835219,
            "f1": 0.584462368789353,
            "f1_weighted": 0.6194808108888522
          },
          {
            "accuracy": 0.6050172159370388,
            "f1": 0.5841312765760142,
            "f1_weighted": 0.6092312768848078
          },
          {
            "accuracy": 0.647319232661092,
            "f1": 0.609085812816468,
            "f1_weighted": 0.6510841899656695
          }
        ]
      }
    ]
  },
  "task_name": "MassiveIntentClassification"
}