{
  "dataset_revision": "1399c76144fd37290681b995c656ef9b2e06e26d",
  "evaluation_time": 50.5599250793457,
  "kg_co2_emissions": null,
  "mteb_version": "1.14.20",
  "scores": {
    "test": [
      {
        "accuracy": 0.26702000000000004,
        "f1": 0.2645652419865254,
        "f1_weighted": 0.2645652419865254,
        "hf_subset": "en",
        "languages": [
          "eng-Latn"
        ],
        "main_score": 0.26702000000000004,
        "scores_per_experiment": [
          {
            "accuracy": 0.2792,
            "f1": 0.2796404644928022,
            "f1_weighted": 0.2796404644928022
          },
          {
            "accuracy": 0.2928,
            "f1": 0.2912445480305535,
            "f1_weighted": 0.29124454803055344
          },
          {
            "accuracy": 0.2462,
            "f1": 0.24451766484362256,
            "f1_weighted": 0.24451766484362256
          },
          {
            "accuracy": 0.2292,
            "f1": 0.22389405772570167,
            "f1_weighted": 0.22389405772570167
          },
          {
            "accuracy": 0.2898,
            "f1": 0.28535751721613667,
            "f1_weighted": 0.28535751721613667
          },
          {
            "accuracy": 0.2654,
            "f1": 0.26324936570662866,
            "f1_weighted": 0.26324936570662866
          },
          {
            "accuracy": 0.2414,
            "f1": 0.23776682086143755,
            "f1_weighted": 0.23776682086143752
          },
          {
            "accuracy": 0.2822,
            "f1": 0.27870507604380046,
            "f1_weighted": 0.27870507604380057
          },
          {
            "accuracy": 0.2836,
            "f1": 0.2837207673971218,
            "f1_weighted": 0.2837207673971218
          },
          {
            "accuracy": 0.2604,
            "f1": 0.25755613754744944,
            "f1_weighted": 0.2575561375474495
          }
        ]
      }
    ]
  },
  "task_name": "AmazonReviewsClassification"
}