{
  "dataset_revision": "d604517c81ca91fe16a244d1248fc021f9ecee7a",
  "evaluation_time": 14.882067441940308,
  "kg_co2_emissions": null,
  "mteb_version": "1.14.20",
  "scores": {
    "test": [
      {
        "accuracy": 0.3824561403508772,
        "f1": 0.3813606702710052,
        "f1_weighted": 0.38203903062509376,
        "hf_subset": "default",
        "languages": [
          "eng-Latn"
        ],
        "main_score": 0.3824561403508772,
        "scores_per_experiment": [
          {
            "accuracy": 0.3503112620260328,
            "f1": 0.3502448671523218,
            "f1_weighted": 0.3506352023511638
          },
          {
            "accuracy": 0.4029428409734012,
            "f1": 0.40232883243727025,
            "f1_weighted": 0.4033053331544243
          },
          {
            "accuracy": 0.3647425014148274,
            "f1": 0.3650635916009863,
            "f1_weighted": 0.36079916933456047
          },
          {
            "accuracy": 0.38398415393322016,
            "f1": 0.38366867170753016,
            "f1_weighted": 0.38264176196095423
          },
          {
            "accuracy": 0.39954725523486134,
            "f1": 0.3920815161988562,
            "f1_weighted": 0.39897430956028357
          },
          {
            "accuracy": 0.378324844368987,
            "f1": 0.3786703684176758,
            "f1_weighted": 0.37666966516346123
          },
          {
            "accuracy": 0.399830220713073,
            "f1": 0.39890347738630866,
            "f1_weighted": 0.4008568841952356
          },
          {
            "accuracy": 0.38115449915110355,
            "f1": 0.38124835954976555,
            "f1_weighted": 0.38126060860144695
          },
          {
            "accuracy": 0.3729485002829655,
            "f1": 0.373086638098066,
            "f1_weighted": 0.3730291254164542
          },
          {
            "accuracy": 0.39077532541029997,
            "f1": 0.38831038016127106,
            "f1_weighted": 0.39221824651295273
          }
        ]
      }
    ]
  },
  "task_name": "TweetSentimentExtractionClassification"
}