{
  "dataset_revision": "4f58c6b202a23cf9a4da393831edf4f9183cad37",
  "evaluation_time": 12.149599552154541,
  "kg_co2_emissions": null,
  "mteb_version": "1.14.20",
  "scores": {
    "test": [
      {
        "accuracy": 0.19770000000000001,
        "f1": 0.17612355674512697,
        "f1_weighted": 0.21416897208856361,
        "hf_subset": "default",
        "languages": [
          "eng-Latn"
        ],
        "main_score": 0.19770000000000001,
        "scores_per_experiment": [
          {
            "accuracy": 0.193,
            "f1": 0.17761960961695156,
            "f1_weighted": 0.2096228825439142
          },
          {
            "accuracy": 0.204,
            "f1": 0.1872535194518794,
            "f1_weighted": 0.22053399480933283
          },
          {
            "accuracy": 0.218,
            "f1": 0.18575462429663966,
            "f1_weighted": 0.23822012805305395
          },
          {
            "accuracy": 0.1985,
            "f1": 0.1729829415624664,
            "f1_weighted": 0.2168845960713393
          },
          {
            "accuracy": 0.1855,
            "f1": 0.1659454413847438,
            "f1_weighted": 0.20080126363516426
          },
          {
            "accuracy": 0.1925,
            "f1": 0.17035628893184931,
            "f1_weighted": 0.20648265337077923
          },
          {
            "accuracy": 0.1795,
            "f1": 0.16168068791485474,
            "f1_weighted": 0.19659029615358933
          },
          {
            "accuracy": 0.198,
            "f1": 0.17201777998015277,
            "f1_weighted": 0.21664902423214485
          },
          {
            "accuracy": 0.225,
            "f1": 0.20027420023496065,
            "f1_weighted": 0.24042394548575502
          },
          {
            "accuracy": 0.183,
            "f1": 0.16735047407677137,
            "f1_weighted": 0.19548093653056278
          }
        ]
      }
    ]
  },
  "task_name": "EmotionClassification"
}