{
  "dataset_revision": "0fd18e25b25c072e09e0d92ab615fda904d66300",
  "evaluation_time": 314.9917356967926,
  "kg_co2_emissions": null,
  "mteb_version": "1.14.19",
  "scores": {
    "test": [
      {
        "accuracy": 0.6532792207792208,
        "f1": 0.6512537032742125,
        "f1_weighted": 0.6512537032742125,
        "hf_subset": "default",
        "languages": [
          "eng-Latn"
        ],
        "main_score": 0.6532792207792208,
        "scores_per_experiment": [
          {
            "accuracy": 0.6512987012987013,
            "f1": 0.6482598151146642,
            "f1_weighted": 0.6482598151146642
          },
          {
            "accuracy": 0.6457792207792208,
            "f1": 0.6449423508725803,
            "f1_weighted": 0.6449423508725802
          },
          {
            "accuracy": 0.6775974025974026,
            "f1": 0.6770100420813397,
            "f1_weighted": 0.6770100420813396
          },
          {
            "accuracy": 0.6652597402597402,
            "f1": 0.6643929357922331,
            "f1_weighted": 0.6643929357922332
          },
          {
            "accuracy": 0.6564935064935065,
            "f1": 0.6563443182771944,
            "f1_weighted": 0.6563443182771945
          },
          {
            "accuracy": 0.6535714285714286,
            "f1": 0.6507157282520496,
            "f1_weighted": 0.6507157282520495
          },
          {
            "accuracy": 0.6376623376623377,
            "f1": 0.6359296869418465,
            "f1_weighted": 0.6359296869418465
          },
          {
            "accuracy": 0.6318181818181818,
            "f1": 0.6278871876672274,
            "f1_weighted": 0.6278871876672273
          },
          {
            "accuracy": 0.6535714285714286,
            "f1": 0.6507663831371825,
            "f1_weighted": 0.6507663831371825
          },
          {
            "accuracy": 0.6597402597402597,
            "f1": 0.6562885846058081,
            "f1_weighted": 0.656288584605808
          }
        ]
      }
    ]
  },
  "task_name": "Banking77Classification"
}