{
  "dataset_revision": "d604517c81ca91fe16a244d1248fc021f9ecee7a",
  "evaluation_time": 23.19157862663269,
  "kg_co2_emissions": null,
  "mteb_version": "1.14.19",
  "scores": {
    "test": [
      {
        "accuracy": 0.5516694963214487,
        "f1": 0.5539384000779678,
        "f1_weighted": 0.5489050610847116,
        "hf_subset": "default",
        "languages": [
          "eng-Latn"
        ],
        "main_score": 0.5516694963214487,
        "scores_per_experiment": [
          {
            "accuracy": 0.5500848896434635,
            "f1": 0.5496644183551852,
            "f1_weighted": 0.5403061983958897
          },
          {
            "accuracy": 0.5503678551216752,
            "f1": 0.5529572921063562,
            "f1_weighted": 0.5491461188417966
          },
          {
            "accuracy": 0.5710243350311262,
            "f1": 0.5739226691245642,
            "f1_weighted": 0.5699323629032803
          },
          {
            "accuracy": 0.5846066779852858,
            "f1": 0.5877719447299498,
            "f1_weighted": 0.5830292995029408
          },
          {
            "accuracy": 0.5316921335597057,
            "f1": 0.5330153216744784,
            "f1_weighted": 0.5314762795249218
          },
          {
            "accuracy": 0.5597057159026598,
            "f1": 0.5634252069522153,
            "f1_weighted": 0.5563659797724367
          },
          {
            "accuracy": 0.5730050933786078,
            "f1": 0.574321494515395,
            "f1_weighted": 0.5687101878921229
          },
          {
            "accuracy": 0.5591397849462365,
            "f1": 0.5599675720966754,
            "f1_weighted": 0.5582003915184119
          },
          {
            "accuracy": 0.4971703452178834,
            "f1": 0.5000643235976744,
            "f1_weighted": 0.49295451104101223
          },
          {
            "accuracy": 0.5398981324278438,
            "f1": 0.5442737576271838,
            "f1_weighted": 0.538929281454303
          }
        ]
      }
    ]
  },
  "task_name": "TweetSentimentExtractionClassification"
}