{
  "dataset_revision": "fad2c6e8459f9e1c45d9315f4953d921437d70f8",
  "evaluation_time": 23.75221276283264,
  "kg_co2_emissions": null,
  "mteb_version": "1.14.20",
  "scores": {
    "test": [
      {
        "accuracy": 0.38547410894418294,
        "f1": 0.36531482624264827,
        "f1_weighted": 0.39449544503960177,
        "hf_subset": "en",
        "languages": [
          "eng-Latn"
        ],
        "main_score": 0.38547410894418294,
        "scores_per_experiment": [
          {
            "accuracy": 0.410221923335575,
            "f1": 0.3966149460035258,
            "f1_weighted": 0.41503037747622984
          },
          {
            "accuracy": 0.3930733019502354,
            "f1": 0.36619199431685107,
            "f1_weighted": 0.41088977327521276
          },
          {
            "accuracy": 0.35810356422326833,
            "f1": 0.34294897921819023,
            "f1_weighted": 0.3655652952012054
          },
          {
            "accuracy": 0.3887020847343645,
            "f1": 0.36434078620422916,
            "f1_weighted": 0.4015953648341578
          },
          {
            "accuracy": 0.39778076664425016,
            "f1": 0.36916064109188457,
            "f1_weighted": 0.403893141065804
          },
          {
            "accuracy": 0.36516476126429054,
            "f1": 0.3406264683166225,
            "f1_weighted": 0.3810138871826857
          },
          {
            "accuracy": 0.3910558170813719,
            "f1": 0.37027643465972093,
            "f1_weighted": 0.39980096478052946
          },
          {
            "accuracy": 0.410221923335575,
            "f1": 0.39267255065327994,
            "f1_weighted": 0.4116368657144727
          },
          {
            "accuracy": 0.3547410894418292,
            "f1": 0.34205775841624786,
            "f1_weighted": 0.358989431968045
          },
          {
            "accuracy": 0.38567585743106925,
            "f1": 0.36825770354593007,
            "f1_weighted": 0.3965393488976747
          }
        ]
      }
    ]
  },
  "task_name": "MassiveScenarioClassification"
}