{
  "dataset_revision": "ae001d0e6b1228650b7bd1c2c65fb50ad11a8aba",
  "evaluation_time": 45.76264429092407,
  "kg_co2_emissions": null,
  "mteb_version": "1.14.20",
  "scores": {
    "test": [
      {
        "accuracy": 0.5134290925672594,
        "f1": 0.34442505881571217,
        "f1_weighted": 0.5670322243379672,
        "hf_subset": "en",
        "languages": [
          "eng-Latn"
        ],
        "main_score": 0.5134290925672594,
        "scores_per_experiment": [
          {
            "accuracy": 0.48700410396716826,
            "f1": 0.32367701196475973,
            "f1_weighted": 0.5297024904242059
          },
          {
            "accuracy": 0.510031919744642,
            "f1": 0.332829492027631,
            "f1_weighted": 0.566124762416928
          },
          {
            "accuracy": 0.5136798905608755,
            "f1": 0.344904639746039,
            "f1_weighted": 0.5709629106850019
          },
          {
            "accuracy": 0.5177838577291382,
            "f1": 0.34974457181757046,
            "f1_weighted": 0.5746122898174282
          },
          {
            "accuracy": 0.5050159598723211,
            "f1": 0.35177007416930645,
            "f1_weighted": 0.5621371367328677
          },
          {
            "accuracy": 0.5216598267213862,
            "f1": 0.35029723918862893,
            "f1_weighted": 0.5718977197062514
          },
          {
            "accuracy": 0.5118559051527588,
            "f1": 0.35338706862794356,
            "f1_weighted": 0.5674194916624873
          },
          {
            "accuracy": 0.5417236662106704,
            "f1": 0.3662568090148249,
            "f1_weighted": 0.5901580155072584
          },
          {
            "accuracy": 0.5047879616963065,
            "f1": 0.3364107762520508,
            "f1_weighted": 0.5630359022825675
          },
          {
            "accuracy": 0.5207478340173278,
            "f1": 0.3349729053483671,
            "f1_weighted": 0.5742715241446745
          }
        ]
      }
    ]
  },
  "task_name": "MTOPIntentClassification"
}